{
  "b": 48,
  "disableInputWhenNotFocused": true,
  "mangledName": "Untitled_32scene",
  "name": "Untitled scene",
  "r": 85,
  "standardSortMethod": true,
  "stopSoundsOnStartup": true,
  "title": "",
  "v": 48,
  "uiSettings": {
    "grid": false,
    "gridType": "rectangular",
    "gridWidth": 32,
    "gridHeight": 32,
    "gridOffsetX": 0,
    "gridOffsetY": 0,
    "gridColor": 10401023,
    "gridAlpha": 0.8,
    "snap": false,
    "zoomFactor": 0.546875,
    "windowMask": false
  },
  "objectsGroups": [],
  "variables": [],
  "instances": [
    {
      "angle": 0,
      "customSize": false,
      "height": 0,
      "keepRatio": true,
      "layer": "",
      "name": "Player",
      "persistentUuid": "fb356299-1c52-42b7-ab1c-62f1a6fe3044",
      "width": 0,
      "x": 237,
      "y": 433,
      "zOrder": 1,
      "numberProperties": [],
      "stringProperties": [],
      "initialVariables": []
    },
    {
      "angle": 0,
      "customSize": true,
      "depth": 1,
      "height": 251,
      "keepRatio": true,
      "layer": "",
      "name": "NewPanelSprite",
      "persistentUuid": "4ae03138-9c93-4963-ad4c-55e403519b0d",
      "width": 999,
      "x": -37,
      "y": 498,
      "zOrder": 2,
      "numberProperties": [],
      "stringProperties": [],
      "initialVariables": []
    }
  ],
  "objects": [
    {
      "adaptCollisionMaskAutomatically": true,
      "assetStoreId": "",
      "name": "Player",
      "type": "Sprite",
      "updateIfNotVisible": false,
      "variables": [],
      "effects": [],
      "behaviors": [
        {
          "acceleration": 1500,
          "canGoDownFromJumpthru": true,
          "canGrabPlatforms": false,
          "canGrabWithoutMoving": true,
          "deceleration": 1500,
          "gravity": 1000,
          "ignoreDefaultControls": false,
          "jumpSpeed": 600,
          "jumpSustainTime": 0.2,
          "ladderClimbingSpeed": 150,
          "maxFallingSpeed": 700,
          "maxSpeed": 200,
          "name": "PlatformerObject",
          "slopeMaxAngle": 60,
          "type": "PlatformBehavior::PlatformerObjectBehavior",
          "useLegacyTrajectory": false,
          "xGrabTolerance": 10,
          "yGrabOffset": 0
        },
        {
          "name": "SmoothCamera",
          "type": "SmoothCamera::SmoothCamera",
          "LeftwardSpeed": 0.9,
          "RightwardSpeed": 0.9,
          "UpwardSpeed": 0.9,
          "DownwardSpeed": 0.9,
          "FollowOnX": true,
          "FollowOnY": true,
          "FollowFreeAreaLeft": 0,
          "FollowFreeAreaRight": 0,
          "FollowFreeAreaTop": 0,
          "FollowFreeAreaBottom": 0,
          "CameraOffsetX": 0,
          "CameraOffsetY": 0,
          "CameraDelay": 0,
          "ForecastTime": 0,
          "ForecastHistoryDuration": 0,
          "LogLeftwardSpeed": 2.0247e-320,
          "LogRightwardSpeed": 2.0247e-320,
          "LogDownwardSpeed": 2.0247e-320,
          "LogUpwardSpeed": 2.0247e-320,
          "DelayedCenterX": 2.0247e-320,
          "DelayedCenterY": 2.0247e-320,
          "ForecastHistoryMeanX": 2.0247e-320,
          "ForecastHistoryMeanY": 2.0247e-320,
          "ForecastHistoryVarianceX": 2.0247e-320,
          "ForecastHistoryCovariance": 2.0247e-320,
          "ForecastHistoryLinearA": 2.0247e-320,
          "ForecastHistoryLinearB": 2.0247e-320,
          "ForecastedX": 2.0247e-320,
          "ForecastedY": 2.0247e-320,
          "ProjectedNewestX": 2.0247e-320,
          "ProjectedNewestY": 2.0247e-320,
          "ProjectedOldestX": 2.0247e-320,
          "ProjectedOldestY": 2.0247e-320,
          "ForecastHistoryVarianceY": 2.0247e-320,
          "Index": 2.0247e-320,
          "CameraDelayCatchUpSpeed": 0,
          "CameraExtraDelay": 2.0247e-320,
          "WaitingSpeedXMax": 2.0247e-320,
          "WaitingSpeedYMax": 2.0247e-320,
          "WaitingEnd": 2.0247e-320,
          "CameraDelayCatchUpDuration": 2.0247e-320,
          "LeftwardSpeedMax": 9000,
          "RightwardSpeedMax": 9000,
          "UpwardSpeedMax": 9000,
          "DownwardSpeedMax": 9000,
          "OldX": 9000.000000007454,
          "OldY": 9000.000000007454,
          "IsCalledManually": false
        },
        {
          "name": "SmoothPlatformerCamera",
          "type": "SmoothCamera::SmoothPlatformerCamera",
          "PlatformerCharacter": "PlatformerObject",
          "SmoothCamera": "SmoothCamera",
          "JumpOriginY": 1.8689350613336503e-308,
          "AirFollowFreeAreaTop": 0,
          "AirFollowFreeAreaBottom": 0,
          "FloorFollowFreeAreaTop": 0,
          "FloorFollowFreeAreaBottom": 0,
          "AirUpwardSpeed": 0.95,
          "AirDownwardSpeed": 0.95,
          "FloorUpwardSpeed": 0.9,
          "FloorDownwardSpeed": 0.9,
          "AirUpwardSpeedMax": 9000,
          "AirDownwardSpeedMax": 9000,
          "FloorUpwardSpeedMax": 9000,
          "FloorDownwardSpeedMax": 9000
        },
        {
          "name": "player_animation_platform",
          "type": "animation_sprite::player_animation_platform",
          "Property": "PlatformerObject",
          "Property2": true
        }
      ],
      "animations": [
        {
          "name": "Idle",
          "useMultipleDirections": false,
          "directions": [
            {
              "looping": true,
              "metadata": "{\"pskl\":{}}",
              "timeBetweenFrames": 0.125,
              "sprites": [
                {
                  "hasCustomCollisionMask": true,
                  "image": "Idle-Sheet",
                  "points": [],
                  "originPoint": {
                    "name": "origine",
                    "x": 0,
                    "y": 0
                  },
                  "centerPoint": {
                    "automatic": true,
                    "name": "centre",
                    "x": 0,
                    "y": 0
                  },
                  "customCollisionMask": [
                    [
                      {
                        "x": 5,
                        "y": 3
                      },
                      {
                        "x": 24,
                        "y": 3
                      },
                      {
                        "x": 24,
                        "y": 32
                      },
                      {
                        "x": 5,
                        "y": 32
                      }
                    ]
                  ]
                },
                {
                  "hasCustomCollisionMask": true,
                  "image": "Idle-Sheet2",
                  "points": [],
                  "originPoint": {
                    "name": "origine",
                    "x": 0,
                    "y": 0
                  },
                  "centerPoint": {
                    "automatic": true,
                    "name": "centre",
                    "x": 0,
                    "y": 0
                  },
                  "customCollisionMask": [
                    [
                      {
                        "x": 5,
                        "y": 3
                      },
                      {
                        "x": 24,
                        "y": 3
                      },
                      {
                        "x": 24,
                        "y": 32
                      },
                      {
                        "x": 5,
                        "y": 32
                      }
                    ]
                  ]
                },
                {
                  "hasCustomCollisionMask": true,
                  "image": "Idle-Sheet3",
                  "points": [],
                  "originPoint": {
                    "name": "origine",
                    "x": 0,
                    "y": 0
                  },
                  "centerPoint": {
                    "automatic": true,
                    "name": "centre",
                    "x": 0,
                    "y": 0
                  },
                  "customCollisionMask": [
                    [
                      {
                        "x": 5,
                        "y": 3
                      },
                      {
                        "x": 24,
                        "y": 3
                      },
                      {
                        "x": 24,
                        "y": 32
                      },
                      {
                        "x": 5,
                        "y": 32
                      }
                    ]
                  ]
                },
                {
                  "hasCustomCollisionMask": true,
                  "image": "Idle-Sheet4",
                  "points": [],
                  "originPoint": {
                    "name": "origine",
                    "x": 0,
                    "y": 0
                  },
                  "centerPoint": {
                    "automatic": true,
                    "name": "centre",
                    "x": 0,
                    "y": 0
                  },
                  "customCollisionMask": [
                    [
                      {
                        "x": 5,
                        "y": 3
                      },
                      {
                        "x": 24,
                        "y": 3
                      },
                      {
                        "x": 24,
                        "y": 32
                      },
                      {
                        "x": 5,
                        "y": 32
                      }
                    ]
                  ]
                }
              ]
            }
          ]
        },
        {
          "name": "move",
          "useMultipleDirections": false,
          "directions": [
            {
              "looping": true,
              "metadata": "{\"pskl\":{}}",
              "timeBetweenFrames": 0.1111111111111111,
              "sprites": [
                {
                  "hasCustomCollisionMask": true,
                  "image": "NewSprite",
                  "points": [],
                  "originPoint": {
                    "name": "origine",
                    "x": 0,
                    "y": 0
                  },
                  "centerPoint": {
                    "automatic": true,
                    "name": "centre",
                    "x": 0,
                    "y": 0
                  },
                  "customCollisionMask": [
                    [
                      {
                        "x": 5,
                        "y": 3
                      },
                      {
                        "x": 24,
                        "y": 3
                      },
                      {
                        "x": 24,
                        "y": 32
                      },
                      {
                        "x": 5,
                        "y": 32
                      }
                    ]
                  ]
                },
                {
                  "hasCustomCollisionMask": true,
                  "image": "NewSprite2",
                  "points": [],
                  "originPoint": {
                    "name": "origine",
                    "x": 0,
                    "y": 0
                  },
                  "centerPoint": {
                    "automatic": true,
                    "name": "centre",
                    "x": 0,
                    "y": 0
                  },
                  "customCollisionMask": [
                    [
                      {
                        "x": 5,
                        "y": 3
                      },
                      {
                        "x": 24,
                        "y": 3
                      },
                      {
                        "x": 24,
                        "y": 32
                      },
                      {
                        "x": 5,
                        "y": 32
                      }
                    ]
                  ]
                },
                {
                  "hasCustomCollisionMask": true,
                  "image": "NewSprite3",
                  "points": [],
                  "originPoint": {
                    "name": "origine",
                    "x": 0,
                    "y": 0
                  },
                  "centerPoint": {
                    "automatic": true,
                    "name": "centre",
                    "x": 0,
                    "y": 0
                  },
                  "customCollisionMask": [
                    [
                      {
                        "x": 5,
                        "y": 3
                      },
                      {
                        "x": 24,
                        "y": 3
                      },
                      {
                        "x": 24,
                        "y": 32
                      },
                      {
                        "x": 5,
                        "y": 32
                      }
                    ]
                  ]
                },
                {
                  "hasCustomCollisionMask": true,
                  "image": "NewSprite4",
                  "points": [],
                  "originPoint": {
                    "name": "origine",
                    "x": 0,
                    "y": 0
                  },
                  "centerPoint": {
                    "automatic": true,
                    "name": "centre",
                    "x": 0,
                    "y": 0
                  },
                  "customCollisionMask": [
                    [
                      {
                        "x": 5,
                        "y": 3
                      },
                      {
                        "x": 24,
                        "y": 3
                      },
                      {
                        "x": 24,
                        "y": 32
                      },
                      {
                        "x": 5,
                        "y": 32
                      }
                    ]
                  ]
                },
                {
                  "hasCustomCollisionMask": true,
                  "image": "NewSprite5",
                  "points": [],
                  "originPoint": {
                    "name": "origine",
                    "x": 0,
                    "y": 0
                  },
                  "centerPoint": {
                    "automatic": true,
                    "name": "centre",
                    "x": 0,
                    "y": 0
                  },
                  "customCollisionMask": [
                    [
                      {
                        "x": 5,
                        "y": 3
                      },
                      {
                        "x": 24,
                        "y": 3
                      },
                      {
                        "x": 24,
                        "y": 32
                      },
                      {
                        "x": 5,
                        "y": 32
                      }
                    ]
                  ]
                },
                {
                  "hasCustomCollisionMask": true,
                  "image": "NewSprite6",
                  "points": [],
                  "originPoint": {
                    "name": "origine",
                    "x": 0,
                    "y": 0
                  },
                  "centerPoint": {
                    "automatic": true,
                    "name": "centre",
                    "x": 0,
                    "y": 0
                  },
                  "customCollisionMask": [
                    [
                      {
                        "x": 5,
                        "y": 3
                      },
                      {
                        "x": 24,
                        "y": 3
                      },
                      {
                        "x": 24,
                        "y": 32
                      },
                      {
                        "x": 5,
                        "y": 32
                      }
                    ]
                  ]
                }
              ]
            }
          ]
        },
        {
          "name": "jump",
          "useMultipleDirections": false,
          "directions": [
            {
              "looping": false,
              "timeBetweenFrames": 0.08,
              "sprites": [
                {
                  "hasCustomCollisionMask": true,
                  "image": "assets\\NewSprite6.png",
                  "points": [],
                  "originPoint": {
                    "name": "origine",
                    "x": 0,
                    "y": 0
                  },
                  "centerPoint": {
                    "automatic": true,
                    "name": "centre",
                    "x": 0,
                    "y": 0
                  },
                  "customCollisionMask": [
                    [
                      {
                        "x": 5,
                        "y": 3
                      },
                      {
                        "x": 24,
                        "y": 3
                      },
                      {
                        "x": 24,
                        "y": 32
                      },
                      {
                        "x": 5,
                        "y": 32
                      }
                    ]
                  ]
                }
              ]
            }
          ]
        },
        {
          "name": "fall",
          "useMultipleDirections": false,
          "directions": [
            {
              "looping": false,
              "timeBetweenFrames": 0.08,
              "sprites": [
                {
                  "hasCustomCollisionMask": true,
                  "image": "assets\\NewSprite.png",
                  "points": [],
                  "originPoint": {
                    "name": "origine",
                    "x": 0,
                    "y": 0
                  },
                  "centerPoint": {
                    "automatic": true,
                    "name": "centre",
                    "x": 0,
                    "y": 0
                  },
                  "customCollisionMask": [
                    [
                      {
                        "x": 5,
                        "y": 3
                      },
                      {
                        "x": 24,
                        "y": 3
                      },
                      {
                        "x": 24,
                        "y": 32
                      },
                      {
                        "x": 5,
                        "y": 32
                      }
                    ]
                  ]
                }
              ]
            }
          ]
        }
      ]
    },
    {
      "assetStoreId": "",
      "bottomMargin": 7,
      "height": 32,
      "leftMargin": 6,
      "name": "NewPanelSprite",
      "rightMargin": 6,
      "texture": "platform.png",
      "tiled": true,
      "topMargin": 7,
      "type": "PanelSpriteObject::PanelSprite",
      "width": 32,
      "variables": [],
      "effects": [],
      "behaviors": [
        {
          "canBeGrabbed": true,
          "name": "Platform",
          "platformType": "NormalPlatform",
          "type": "PlatformBehavior::PlatformBehavior",
          "yGrabOffset": 0
        }
      ]
    }
  ],
  "objectsFolderStructure": {
    "folderName": "__ROOT",
    "children": [
      {
        "objectName": "Player"
      },
      {
        "objectName": "NewPanelSprite"
      }
    ]
  },
  "events": [
    {
      "type": "BuiltinCommonInstructions::Standard",
      "conditions": [],
      "actions": [
        {
          "type": {
            "value": "animation_sprite::player_animation_platform::JUMP_animation"
          },
          "parameters": [
            "Player",
            "player_animation_platform",
            "\"jump\"",
            ""
          ]
        },
        {
          "type": {
            "value": "animation_sprite::player_animation_platform::fall_animation"
          },
          "parameters": [
            "Player",
            "player_animation_platform",
            "\"fall\"",
            ""
          ]
        },
        {
          "type": {
            "value": "animation_sprite::player_animation_platform::idle_animation"
          },
          "parameters": [
            "Player",
            "player_animation_platform",
            "\"Idle\"",
            ""
          ]
        },
        {
          "type": {
            "value": "animation_sprite::player_animation_platform::move_animation"
          },
          "parameters": [
            "Player",
            "player_animation_platform",
            "\"move\"",
            ""
          ]
        },
        {
          "type": {
            "value": "ZoomCamera"
          },
          "parameters": [
            "",
            "1.7",
            "",
            "0"
          ]
        }
      ]
    }
  ],
  "layers": [
    {
      "ambientLightColorB": 200,
      "ambientLightColorG": 200,
      "ambientLightColorR": 200,
      "camera3DFarPlaneDistance": 10000,
      "camera3DFieldOfView": 45,
      "camera3DNearPlaneDistance": 3,
      "cameraType": "",
      "followBaseLayerCamera": false,
      "isLightingLayer": false,
      "isLocked": false,
      "name": "",
      "renderingType": "",
      "visibility": true,
      "cameras": [
        {
          "defaultSize": true,
          "defaultViewport": true,
          "height": 0,
          "viewportBottom": 1,
          "viewportLeft": 0,
          "viewportRight": 1,
          "viewportTop": 0,
          "width": 0
        }
      ],
      "effects": [
        {
          "effectType": "Scene3D::HemisphereLight",
          "name": "3D Light",
          "doubleParameters": {
            "elevation": 45,
            "intensity": 1,
            "rotation": 0
          },
          "stringParameters": {
            "groundColor": "64;64;64",
            "skyColor": "255;255;255",
            "top": "Y-"
          },
          "booleanParameters": {}
        }
      ]
    }
  ],
  "behaviorsSharedData": [
    {
      "name": "Animation",
      "type": "AnimatableCapability::AnimatableBehavior"
    },
    {
      "name": "Effect",
      "type": "EffectCapability::EffectBehavior"
    },
    {
      "name": "Flippable",
      "type": "FlippableCapability::FlippableBehavior"
    },
    {
      "name": "Opacity",
      "type": "OpacityCapability::OpacityBehavior"
    },
    {
      "name": "Platform",
      "type": "PlatformBehavior::PlatformBehavior"
    },
    {
      "name": "PlatformerObject",
      "type": "PlatformBehavior::PlatformerObjectBehavior"
    },
    {
      "name": "Resizable",
      "type": "ResizableCapability::ResizableBehavior"
    },
    {
      "name": "Scale",
      "type": "ScalableCapability::ScalableBehavior"
    },
    {
      "name": "SmoothCamera",
      "type": "SmoothCamera::SmoothCamera"
    },
    {
      "name": "SmoothPlatformerCamera",
      "type": "SmoothCamera::SmoothPlatformerCamera"
    },
    {
      "name": "player_animation_platform",
      "type": "animation_sprite::player_animation_platform"
    }
  ]
}